logprise/__init__.py
logprise/__init__.pyi
logprise/py.typed
logprise-1.3.2.dist-info/METADATA
logprise-1.3.2.dist-info/WHEEL
logprise-1.3.2.dist-info/licenses/LICENSE
logprise-1.3.2.dist-info/RECORD
