Metadata-Version: 2.4
Name: logprise
Version: 1.3.2
Summary: A package integrating loguru and apprise for logging and notifications
License: MIT
License-File: LICENSE
Author: Steven Van Ingelgem
Author-email: steven@vaningelgem.be
Requires-Python: >=3.10
Classifier: License :: OSI Approved :: MIT License
Classifier: Programming Language :: Python :: 3
Classifier: Programming Language :: Python :: 3.10
Classifier: Programming Language :: Python :: 3.11
Classifier: Programming Language :: Python :: 3.12
Classifier: Programming Language :: Python :: 3.13
Classifier: Programming Language :: Python :: 3.14
Requires-Dist: apprise
Requires-Dist: loguru
Requires-Dist: urllib3 (<3)
Project-URL: Repository, https://github.com/svaningelgem/logprise
